{"MoKLozNHu0G/f4/Y4m4MgQ==":"mbr.jpg","GMi/rhZOjh7agrCnlVdvXw==":"mbr.jpeg","I5zFpay5B7b6lGEyfLv6oQ==":"photo-1438761681033-6461ffad8d80.jpeg","VRYRw+jknxnq4q/GE/OqAA==":"mbr-1.jpeg","tOBVHH+XG7EvpU2zCenKCw==":"mbr.png","vIGQwVjQHdTKoh4sCa9Ztw==":"mbr-1.jpg","xVg/yv8ItsxKADXgVzWHQQ==":"mbr-2.jpg","EOY6IQ9RgO3q21wi/Ks+8w==":"mbr-3.jpg","24Q556LhnJrv0jkBPMXdYQ==":"3%20(1)-400x501.jpg","pJ9RV1ppgklIMh6QZ5CqTg==":"2%20(1)-600x798.jpg","YEuWQzXL38DPSq7uoFGtYw==":"1%20(1)-400x400.jpg","KmS8zTC0ywauaNGT/AVdow==":"mbr-1920x1279.jpg","Eb0hLTjP74AbMESg5gd1Fw==":"mbr-1076x717.jpg","IrYn1Qg+06memzrx1oE2HQ==":"singles-1080x1080.png","0cm3rroXKymu+XanmKlkWg==":"singles%20(1)%20pink-1080x1080.png","1dA3U/VY1srBIFQhY9mxKA==":"singles%20(1)-1080x1080.png","EjCiX+XNBKsZpM9UUbxXbw==":"singles%20(2)-1080x1080.png","/4G4Y7Eisc7mRUWTH0FDTg==":"match%202-1080x1080.png","C9xHPoBF7qNCZMhOX2nYuQ==":"mbr-1-1076x717.jpg","bE1EuAE6PvoskEpM2veWgA==":"mbr-1836x1033.jpg","9zCKTgcNv5Vj1mW6qum2dw==":"mbr-1076x718.jpg","CznADm6Peg7H6PkBa7Qe9Q==":"new%20png-1080x1080.png","Zw1DSjXJxLT+KCGGPbruvw==":"mbr-2-1076x717.jpg","3NBVt0Skionf+IVB94ZbPQ==":"mbr-1920x1281.jpg","ZXF4wnhAXolkYFsJaJCkmw==":"match%2022-600x600.png","4JokqAnm8SDopNd4fB2rrQ==":"match%201-600x600.png","Fz7OCUqtTd5w+xJ9hwNfDw==":"match%203-600x600.png","lgNZlJ7xMRwhLwXfagaSMg==":"2905048-512x512.png"}